odoo/addons/coupon_criteria_multi_product/README.rst
odoo/addons/coupon_criteria_multi_product/__init__.py
odoo/addons/coupon_criteria_multi_product/__manifest__.py
odoo/addons/coupon_criteria_multi_product/i18n/coupon_criteria_multi_product.pot
odoo/addons/coupon_criteria_multi_product/i18n/es.po
odoo/addons/coupon_criteria_multi_product/migrations/15.0.1.0.0/pre-migration.py
odoo/addons/coupon_criteria_multi_product/models/__init__.py
odoo/addons/coupon_criteria_multi_product/models/coupon_criteria.py
odoo/addons/coupon_criteria_multi_product/models/coupon_program.py
odoo/addons/coupon_criteria_multi_product/readme/CONFIGURE.rst
odoo/addons/coupon_criteria_multi_product/readme/CONTRIBUTORS.rst
odoo/addons/coupon_criteria_multi_product/readme/DESCRIPTION.rst
odoo/addons/coupon_criteria_multi_product/security/ir.model.access.csv
odoo/addons/coupon_criteria_multi_product/static/description/icon.png
odoo/addons/coupon_criteria_multi_product/static/description/icon.svg
odoo/addons/coupon_criteria_multi_product/static/description/index.html
odoo/addons/coupon_criteria_multi_product/tests/__init__.py
odoo/addons/coupon_criteria_multi_product/tests/test_sale_coupon_criteria_multi_product.py
odoo/addons/coupon_criteria_multi_product/views/sale_coupon_program_views.xml
odoo_addon_coupon_criteria_multi_product-15.0.1.0.1.dist-info/METADATA
odoo_addon_coupon_criteria_multi_product-15.0.1.0.1.dist-info/WHEEL
odoo_addon_coupon_criteria_multi_product-15.0.1.0.1.dist-info/top_level.txt
odoo_addon_coupon_criteria_multi_product-15.0.1.0.1.dist-info/RECORD
